bloqade/shuttle/__init__.py
bloqade/shuttle/arch.py
bloqade/shuttle/prelude.py
bloqade/shuttle/analysis/__init__.py
bloqade/shuttle/analysis/runtime.py
bloqade/shuttle/analysis/zone/__init__.py
bloqade/shuttle/analysis/zone/analysis.py
bloqade/shuttle/analysis/zone/lattice.py
bloqade/shuttle/analysis/zone/impl/__init__.py
bloqade/shuttle/analysis/zone/impl/grid.py
bloqade/shuttle/analysis/zone/impl/py.py
bloqade/shuttle/analysis/zone/impl/spec.py
bloqade/shuttle/codegen/__init__.py
bloqade/shuttle/codegen/taskgen.py
bloqade/shuttle/dialects/__init__.py
bloqade/shuttle/dialects/action/__init__.py
bloqade/shuttle/dialects/action/_dialect.py
bloqade/shuttle/dialects/action/_interface.py
bloqade/shuttle/dialects/action/stmts.py
bloqade/shuttle/dialects/atom/__init__.py
bloqade/shuttle/dialects/atom/_dialect.py
bloqade/shuttle/dialects/atom/_interface.py
bloqade/shuttle/dialects/atom/stmts.py
bloqade/shuttle/dialects/atom/types.py
bloqade/shuttle/dialects/filled/__init__.py
bloqade/shuttle/dialects/filled/_dialect.py
bloqade/shuttle/dialects/filled/_interface.py
bloqade/shuttle/dialects/filled/concrete.py
bloqade/shuttle/dialects/filled/stmts.py
bloqade/shuttle/dialects/filled/types.py
bloqade/shuttle/dialects/gate/__init__.py
bloqade/shuttle/dialects/gate/_dialect.py
bloqade/shuttle/dialects/gate/_interface.py
bloqade/shuttle/dialects/gate/runtime.py
bloqade/shuttle/dialects/gate/stmts.py
bloqade/shuttle/dialects/init/__init__.py
bloqade/shuttle/dialects/init/_dialect.py
bloqade/shuttle/dialects/init/_interface.py
bloqade/shuttle/dialects/init/runtime.py
bloqade/shuttle/dialects/init/stmts.py
bloqade/shuttle/dialects/measure/__init__.py
bloqade/shuttle/dialects/measure/_dialect.py
bloqade/shuttle/dialects/measure/_interface.py
bloqade/shuttle/dialects/measure/runtime.py
bloqade/shuttle/dialects/measure/stmts.py
bloqade/shuttle/dialects/measure/types.py
bloqade/shuttle/dialects/path/__init__.py
bloqade/shuttle/dialects/path/_dialect.py
bloqade_shuttle-0.8.3.dist-info/METADATA
bloqade_shuttle-0.8.3.dist-info/WHEEL
bloqade_shuttle-0.8.3.dist-info/licenses/LICENSE
bloqade_shuttle-0.8.3.dist-info/RECORD
