Metadata-Version: 2.4
Name: bloqade-shuttle
Version: 0.8.3
Summary: SDK for programming and simulating atom shuttling operation in neutral atom quantum computers.
Author-email: "QuEra Computing Inc." <info@quera.com>
License-File: LICENSE
Requires-Python: >=3.10
Requires-Dist: bloqade-circuit<0.8.0-dev,>=0.6.0
Requires-Dist: bloqade-geometry~=0.3.0
Requires-Dist: kirin-toolchain<0.18.0-dev,>=0.17.17
Provides-Extra: visualization
Requires-Dist: matplotlib>=3.9.4; extra == 'visualization'
